AmberPy-0.0.1.data/scripts/james
amberpy/__init__.py
amberpy/config.py
amberpy/crossbow.py
amberpy/experiments.py
amberpy/md_setup.py
amberpy/simulation.py
amberpy/tools.py
amberpy/utilities.py
amberpy/cosolvents/__init__.py
AmberPy-0.0.1.dist-info/LICENSE
AmberPy-0.0.1.dist-info/METADATA
AmberPy-0.0.1.dist-info/WHEEL
AmberPy-0.0.1.dist-info/top_level.txt
AmberPy-0.0.1.dist-info/RECORD
